haruhi_dl/HaruhiDL.py
haruhi_dl/__init__.py
haruhi_dl/__main__.py
haruhi_dl/aes.py
haruhi_dl/cache.py
haruhi_dl/compat.py
haruhi_dl/options.py
haruhi_dl/playwright.py
haruhi_dl/socks.py
haruhi_dl/update.py
haruhi_dl/utils.py
haruhi_dl/version.py
haruhi_dl/downloader/__init__.py
haruhi_dl/downloader/common.py
haruhi_dl/downloader/dash.py
haruhi_dl/downloader/external.py
haruhi_dl/downloader/f4m.py
haruhi_dl/downloader/fragment.py
haruhi_dl/downloader/hls.py
haruhi_dl/downloader/http.py
haruhi_dl/downloader/ism.py
haruhi_dl/downloader/niconico.py
haruhi_dl/downloader/rtmp.py
haruhi_dl/downloader/rtsp.py
haruhi_dl/extractor/__init__.py
haruhi_dl/extractor/abc.py
haruhi_dl/extractor/abcnews.py
haruhi_dl/extractor/abcotvs.py
haruhi_dl/extractor/academicearth.py
haruhi_dl/extractor/acast.py
haruhi_dl/extractor/adn.py
haruhi_dl/extractor/adobeconnect.py
haruhi_dl/extractor/adobepass.py
haruhi_dl/extractor/adobetv.py
haruhi_dl/extractor/adultswim.py
haruhi_dl/extractor/aenetworks.py
haruhi_dl/extractor/afreecatv.py
haruhi_dl/extractor/agora.py
haruhi_dl/extractor/airmozilla.py
haruhi_dl/extractor/albicla.py
haruhi_dl/extractor/aliexpress.py
haruhi_dl/extractor/aljazeera.py
haruhi_dl/extractor/allocine.py
haruhi_dl/extractor/alphaporno.py
haruhi_dl/extractor/amara.py
haruhi_dl/extractor/amcnetworks.py
haruhi_dl/extractor/americastestkitchen.py
haruhi_dl/extractor/amp.py
haruhi_dl/extractor/animeondemand.py
haruhi_dl/extractor/anvato.py
haruhi_dl/extractor/aol.py
haruhi_dl/extractor/apa.py
haruhi_dl/extractor/aparat.py
haruhi_dl/extractor/appleconnect.py
haruhi_dl/extractor/applepodcasts.py
haruhi_dl/extractor/appletrailers.py
haruhi_dl/extractor/archiveorg.py
haruhi_dl/extractor/arcpublishing.py
haruhi_dl/extractor/ard.py
haruhi_dl/extractor/arkena.py
haruhi_dl/extractor/arnes.py
haruhi_dl/extractor/arte.py
haruhi_dl/extractor/asiancrush.py
haruhi_dl/extractor/atresplayer.py
haruhi_dl/extractor/atttechchannel.py
haruhi_dl/extractor/atvat.py
haruhi_dl/extractor/audimedia.py
haruhi_dl-2021.8.1.dist-info/AUTHORS
haruhi_dl-2021.8.1.dist-info/LICENSE
haruhi_dl-2021.8.1.dist-info/METADATA
haruhi_dl-2021.8.1.dist-info/WHEEL
haruhi_dl-2021.8.1.dist-info/entry_points.txt
haruhi_dl-2021.8.1.dist-info/top_level.txt
haruhi_dl-2021.8.1.dist-info/RECORD
