Metadata-Version: 2.1
Name: haruhi_dl
Version: 2021.8.1
Summary: Online video downloader
Home-page: https://git.sakamoto.pl/laudom/haruhi-dl
Author: Laura Liberda | Dominika Liberda | Patrycja Liberda
Author-email: hdl@haruhi.download
Maintainer: Dominika Liberda
Maintainer-email: ja@sdomi.pl
License: LGPL-3.0-or-later
Platform: UNKNOWN
Classifier: Topic :: Multimedia :: Video
Classifier: Development Status :: 5 - Production/Stable
Classifier: Environment :: Console
Classifier: License :: OSI Approved :: GNU Lesser General Public License v3 or later (LGPLv3+)
Classifier: Programming Language :: Python
Classifier: Programming Language :: Python :: 3
Classifier: Programming Language :: Python :: 3.6
Classifier: Programming Language :: Python :: 3.7
Classifier: Programming Language :: Python :: 3.8
Classifier: Programming Language :: Python :: 3.9
Classifier: Programming Language :: Python :: Implementation
Classifier: Programming Language :: Python :: Implementation :: CPython
Classifier: Programming Language :: Python :: Implementation :: PyPy
License-File: LICENSE
License-File: AUTHORS
